{
  "nuget": {
    "source": "https://api.nuget.org/v3/index.json"
  },
  "releases": [
    {
      "name": "DotNet.Basics",
      "version": "10.0.0",
      "prerelease": "beta.3.3"
    },
    {
      "name": "DotNet.Basics.Autofac",
      "version": "4.9.4",
      "prerelease": "beta.1.0"
    },
    {
      "name": "DotNet.Basics.Cli",
      "version": "10.0.0",
      "prerelease": "beta.2.6"
    },
    {
      "name": "DotNet.Basics.Net.Http",
      "version": "10.0.0",
      "prerelease": "beta.1.0"
    },
    {
      "name": "DotNet.Basics.Pipelines",
      "version": "10.0.0",
      "prerelease": "beta.1.0"
    },
    {
      "name": "DotNet.Basics.PowerShell",
      "version": "7.0.0",
      "prerelease": "beta.2.2"
    },
    {
      "name": "DotNet.Basics.SeriLog",
      "version": "2.8.1",
      "prerelease": "beta.1.0"
    },
    {
      "name": "DotNet.Basics.SevenZip",
      "version": "19.00.0",
      "prerelease": "beta.2.2"
    }
  ],
  "tests": [
    "DotNet.Basics.Tests"
  ]
}